tssolver/__init__.py
tssolver/__main__.py
tssolver/board.py
tssolver/example_grids.py
tssolver/interface.py
tssolver/solver.py
tssolver-0.0.2.dist-info/LICENSE
tssolver-0.0.2.dist-info/METADATA
tssolver-0.0.2.dist-info/WHEEL
tssolver-0.0.2.dist-info/entry_points.txt
tssolver-0.0.2.dist-info/top_level.txt
tssolver-0.0.2.dist-info/RECORD
