Metadata-Version: 2.1
Name: tssolver
Version: 0.0.2
Summary: A classic sudoku puzzle solver with a tkinter interface.
Home-page: https://gitlab.com/emerac/tkinter-sudoku-solver
Author: emerac
Author-email: 7785766-emerac@users.noreply.gitlab.com
License: GPLv3
Keywords: tkinter,sudoku,puzzle,solver
Platform: UNKNOWN
Classifier: Development Status :: 4 - Beta
Classifier: Intended Audience :: End Users/Desktop
Classifier: License :: OSI Approved :: GNU General Public License v3 or later (GPLv3+)
Classifier: Operating System :: POSIX :: Linux
Classifier: Programming Language :: Python :: 3 :: Only
Classifier: Programming Language :: Python :: 3.9
Classifier: Programming Language :: Python :: 3.8
Classifier: Programming Language :: Python :: 3.7
Classifier: Topic :: Utilities
Requires-Python: >=3.7
